Metadata-Version: 2.1
Name: sphinx_press_theme
Version: 0.9.1
Summary: A Sphinx-doc theme based on Vuepress
Home-page: https://schettino72.github.io/sphinx_press_site/
Author: Eduardo Naufel Schettino <schetino72>
License: MIT
Project-URL: Documentation, https://schettino72.github.io/sphinx_press_site/
Project-URL: Source, https://github.com/schettino72/sphinx_press_theme
Project-URL: Tracker, https://schettino72.github.io/sphinx_press_site/issues
Keywords: sphinx doc theme vue.js
Classifier: Framework :: Sphinx
Classifier: Framework :: Sphinx :: Theme
Classifier: Development Status :: 4 - Beta
Classifier: License :: OSI Approved :: MIT License
Classifier: Environment :: Console
Classifier: Environment :: Web Environment
Classifier: Intended Audience :: Developers
Classifier: Programming Language :: Python :: 3
Classifier: Programming Language :: Python :: 3.6
Classifier: Programming Language :: Python :: 3.7
Classifier: Programming Language :: Python :: 3.8
Classifier: Programming Language :: Python :: 3.9
Classifier: Operating System :: OS Independent
Classifier: Topic :: Documentation
Classifier: Topic :: Software Development :: Documentation
License-File: LICENSE
License-File: AUTHORS
Requires-Dist: sphinx>=4.0.1
